config/geoapi.yaml
config/openapi_templates/README.md
config/openapi_templates/yaml/additionalParameter.yaml
config/openapi_templates/yaml/bbox.yaml
config/openapi_templates/yaml/binaryInputValue.yaml
config/openapi_templates/yaml/confClasses.yaml
config/openapi_templates/yaml/descriptionType.yaml
config/openapi_templates/yaml/exception.yaml
config/openapi_templates/yaml/execute.yaml
config/openapi_templates/yaml/format.yaml
config/openapi_templates/yaml/inlineOrRefData.yaml
config/openapi_templates/yaml/inputDescription.yaml
config/openapi_templates/yaml/inputValue.yaml
config/openapi_templates/yaml/inputValueNoObject.yaml
config/openapi_templates/yaml/jobControlOptions.yaml
config/openapi_templates/yaml/jobList.yaml
config/openapi_templates/yaml/landingPage.yaml
config/openapi_templates/yaml/link.yaml
config/openapi_templates/yaml/metadata.yaml
config/openapi_templates/yaml/openapi_schema.yaml
config/openapi_templates/yaml/output.yaml
config/openapi_templates/yaml/outputDescription.yaml
config/openapi_templates/yaml/process.yaml
config/openapi_templates/yaml/processList.yaml
config/openapi_templates/yaml/processSummary.yaml
config/openapi_templates/yaml/qualifiedInputValue.yaml
config/openapi_templates/yaml/reference.yaml
config/openapi_templates/yaml/results.yaml
config/openapi_templates/yaml/schema.yaml
config/openapi_templates/yaml/statusCode.yaml
config/openapi_templates/yaml/statusInfo.yaml
config/openapi_templates/yaml/subscriber.yaml
config/openapi_templates/yaml/transmissionMode.yaml
config/tasktable.json
rs_dpr_service/__init__.py
rs_dpr_service/call_dask.py
rs_dpr_service/conversion_processor.py
rs_dpr_service/jobs_table.py
rs_dpr_service/main.py
rs_dpr_service/openapi_validation.py
rs_dpr_service/processors.py
rs_dpr_service/safe_to_zarr.py
rs_dpr_service/utils/__init__.py
rs_dpr_service/utils/init_opentelemetry.py
rs_dpr_service/utils/logging.py
rs_dpr_service/utils/utils.py
rs_dpr_service-0.2.dist-info/METADATA
rs_dpr_service-0.2.dist-info/WHEEL
rs_dpr_service-0.2.dist-info/RECORD
